{"{\"body\": \"{\\\"passphrase\\\": \\\"correct horse battery staple profanity oil chewy\\\", \\\"username\\\": \\\"journalist\\\"}\", \"method\": \"POST\", \"path_query\": \"api/v1/token\", \"timeout\": 20}+1": "{\"status\": 200, \"body\": \"{\\n  \\\"expiration\\\": \\\"2020-10-15T07:00:30.316050Z\\\", \\n  \\\"journalist_first_name\\\": \\\"\\\", \\n  \\\"journalist_last_name\\\": \\\"\\\", \\n  \\\"journalist_uuid\\\": \\\"122ef3e3-2577-4638-b66a-671fe423f216\\\", \\n  \\\"token\\\": \\\"eyJpYXQiOjE2MDI3MTY0MzAsImV4cCI6MTYwMjc0NTIzMCwiYWxnIjoiSFMyNTYifQ.eyJpZCI6MX0.kmFARZQ8lI0PrzLgHw3UGTBRX84oI9DhB-E-eJIIsg4\\\"\\n}\\n\", \"headers\": {\"Content-Type\": \"application/json\", \"Content-Length\": \"313\", \"Server\": \"Werkzeug/0.16.0 Python/3.5.2\", \"Date\": \"Wed, 14 Oct 2020 23:00:30 GMT\"}, \"version\": \"0.3.0\\n\"}"}